{
    "id": "test",
    "eFormType": "repair",
    "lang": "cn",
    "institutionID": "test",
    "version": "0.1",
    "published": true,
    "content": [{
            "id": "RESTORATION",
            "fieldType": "select",
            "fieldValue": "",
            "displayName": "Restoration",
            "description": "",
            "childLabel": "修复类型",
            "imgPath": "",
            "show": true,
            "required": true,
            "child": [{
                    "id": "CROWN",
                    "fieldType": "select",
                    "fieldValue": "",
                    "displayName": "冠",
                    "description": "",
                    "childLabel": "",
                    "imgPath": "",
                    "show": true,
                    "required": true,
                    "child": []
                }, {
                    "id": "PONTIC",
                    "fieldType": "select",
                    "fieldValue": "",
                    "displayName": "缺失牙",
                    "description": "",
                    "childLabel": "",
                    "imgPath": "",
                    "show": true,
                    "required": true,
                    "child": []
                }, {
                    "id": "VENEER",
                    "fieldType": "select",
                    "fieldValue": "",
                    "displayName": "贴面",
                    "description": "",
                    "childLabel": "",
                    "imgPath": "",
                    "show": true,
                    "required": true,
                    "child": []
                }, {
                    "id": "INLAY",
                    "fieldType": "select",
                    "fieldValue": "",
                    "displayName": "嵌体",
                    "description": "",
                    "childLabel": "",
                    "imgPath": "",
                    "show": true,
                    "required": true,
                    "child": []
                }, {
                    "id": "ANTAGONIST",
                    "fieldType": "select",
                    "fieldValue": "",
                    "displayName": "对颌牙",
                    "description": "",
                    "childLabel": "",
                    "imgPath": "",
                    "show": true,
                    "required": true,
                    "child": []
                }
            ]
        }, {
            "id": "IMPLANT",
            "fieldType": "select",
            "fieldValue": "",
            "displayName": "Implant",
            "description": "",
            "childLabel": "基台类型",
            "imgPath": "",
            "show": true,
            "required": true,
            "child": [{
                    "id": "STOCK_ABUTMENT",
                    "fieldType": "select",
                    "fieldValue": "",
                    "displayName": "成品基台",
                    "description": "",
                    "childLabel": "",
                    "imgPath": "",
                    "show": true,
                    "required": true,
                    "child": []
                }, {
                    "id": "CUSTOM_ABUTMENT",
                    "fieldType": "select",
                    "fieldValue": "",
                    "displayName": "个性化基台",
                    "description": "",
                    "childLabel": "",
                    "imgPath": "",
                    "show": true,
                    "required": true,
                    "child": []
                }, {
                    "id": "INTERGRATED_ABUTMENT",
                    "fieldType": "select",
                    "fieldValue": "",
                    "displayName": "基台一体化",
                    "description": "",
                    "childLabel": "",
                    "imgPath": "",
                    "show": true,
                    "required": true,
                    "child": []
                }
            ]
        }
    ]
}
